opaca/__init__.py
opaca/abstract_agent.py
opaca/container.py
opaca/decorators.py
opaca/models.py
opaca/routes.py
opaca/utils.py
opaca-0.0.6.dist-info/licenses/LICENSE
opaca-0.0.6.dist-info/METADATA
opaca-0.0.6.dist-info/WHEEL
opaca-0.0.6.dist-info/top_level.txt
opaca-0.0.6.dist-info/RECORD
