Metadata-Version: 2.4
Name: opaca
Version: 0.0.6
Summary: Provides helpful tools for building your own OPACA Agent Container.
Author-email: Oskar Felix Kupke <oskarfelix.kupke@gt-arc.com>, Tobias Küster <tobias.kuester@gt-arc.com>, Robert Karsten Strehlow <robert.strehlow@gt-arc.com>
License-Expression: LicenseRef-OPACA
Project-URL: Repository, https://github.com/GT-ARC/opaca-python-sdk
Project-URL: Changelog, https://github.com/GT-ARC/opaca-python-sdk/blob/main/CHANGELOG.md
Requires-Python: >=3.10
License-File: LICENSE
Requires-Dist: pydantic>=2.12.0
Requires-Dist: fastapi>=0.119.0
Requires-Dist: uvicorn[standard]>=0.37.0
Requires-Dist: starlette>=0.48.0
Dynamic: license-file
